README.rst
pyproject.toml
RsMxo/RsMxo.py
RsMxo/__init__.py
RsMxo/enums.py
RsMxo/py.typed.py
RsMxo/repcap.py
RsMxo.egg-info/PKG-INFO
RsMxo.egg-info/SOURCES.txt
RsMxo.egg-info/dependency_links.txt
RsMxo.egg-info/requires.txt
RsMxo.egg-info/top_level.txt
RsMxo/CustomFiles/__init__.py
RsMxo/CustomFiles/events.py
RsMxo/CustomFiles/utilities.py
RsMxo/Implementations/AutoScale.py
RsMxo/Implementations/Hdefinition.py
RsMxo/Implementations/Run.py
RsMxo/Implementations/Trfs.py
RsMxo/Implementations/TriggerInvoke.py
RsMxo/Implementations/__init__.py
RsMxo/Implementations/Acquire/Points.py
RsMxo/Implementations/Acquire/RollMode.py
RsMxo/Implementations/Acquire/Segmented.py
RsMxo/Implementations/Acquire/SymbolRate.py
RsMxo/Implementations/Acquire/__init__.py
RsMxo/Implementations/Acquire/History/Play.py
RsMxo/Implementations/Acquire/History/__init__.py
RsMxo/Implementations/Calculate/__init__.py
RsMxo/Implementations/Calculate/Math/EnvSelection.py
RsMxo/Implementations/Calculate/Math/Label.py
RsMxo/Implementations/Calculate/Math/State.py
RsMxo/Implementations/Calculate/Math/Unit.py
RsMxo/Implementations/Calculate/Math/__init__.py
RsMxo/Implementations/Calculate/Math/Data/Header.py
RsMxo/Implementations/Calculate/Math/Data/Stype.py
RsMxo/Implementations/Calculate/Math/Data/Values.py
RsMxo/Implementations/Calculate/Math/Data/ValuesPartial.py
RsMxo/Implementations/Calculate/Math/Data/__init__.py
RsMxo/Implementations/Calculate/Math/Expression/Define.py
RsMxo/Implementations/Calculate/Math/Expression/__init__.py
RsMxo/Implementations/Calculate/Math/Vertical/Offset.py
RsMxo/Implementations/Calculate/Math/Vertical/__init__.py
RsMxo/Implementations/Calculate/Math/Vertical/Scale/Mode.py
RsMxo/Implementations/Calculate/Math/Vertical/Scale/Value.py
RsMxo/Implementations/Calculate/Math/Vertical/Scale/__init__.py
RsMxo/Implementations/Calculate/Spectrum/Pexcursion.py
RsMxo/Implementations/Calculate/Spectrum/Source.py
RsMxo/Implementations/Calculate/Spectrum/State.py
RsMxo/Implementations/Calculate/Spectrum/Threshold.py
RsMxo/Implementations/Calculate/Spectrum/__init__.py
RsMxo/Implementations/Calculate/Spectrum/Frequency/Center.py
