Metadata-Version: 2.4
Name: RsMxo
Version: 2.7.3
Summary: MXO Series Digital Oscilloscopes Driver Remote-control module
Author: Rohde & Schwarz GmbH & Co. KG
Maintainer: Rohde & Schwarz GmbH & Co. KG
License-Expression: MIT
Project-URL: Documentation, https://RsMxo.readthedocs.io/
Project-URL: Examples, https://github.com/Rohde-Schwarz/Examples/
Keywords: MXO,MXO3,MXO4,MXO5,MXO44,MXO58
Classifier: Development Status :: 5 - Production/Stable
Classifier: Topic :: Scientific/Engineering :: Instrument Drivers
Classifier: Programming Language :: Python :: 3
Classifier: Programming Language :: Python :: 3.8
Classifier: Programming Language :: Python :: 3.9
Classifier: Programming Language :: Python :: 3.10
Classifier: Programming Language :: Python :: 3.11
Classifier: Programming Language :: Python :: 3.12
Classifier: Programming Language :: Python :: 3.13
Requires-Python: >=3.8
Requires-Dist: pyvisa>=1.13.0
Requires-Dist: typing-extensions>=4.0.0
